EndoriumUtils/__init__.py
EndoriumUtils/auth_utils.py
EndoriumUtils/config_utils.py
EndoriumUtils/file_utils.py
EndoriumUtils/log_utils.py
EndoriumUtils/version_utils.py
endoriumutils-1.2.5.dist-info/METADATA
endoriumutils-1.2.5.dist-info/WHEEL
endoriumutils-1.2.5.dist-info/top_level.txt
endoriumutils-1.2.5.dist-info/RECORD
