Metadata-Version: 2.4
Name: EndoriumUtils
Version: 1.2.5
Summary: Utilitaires communs pour les projets Endorium
Home-page: https://github.com/NergYR/EndoriumUtils
Author: Energetiq
Author-email: Energetiq <energetiq@outlook.com>
License: MIT
Project-URL: Bug Reports, https://github.com/NergYR/EndoriumUtils/issues
Project-URL: Source, https://github.com/NergYR/EndoriumUtils
Keywords: logging,version management,utilities,configuration
Classifier: Programming Language :: Python :: 3
Classifier: Operating System :: OS Independent
Classifier: Development Status :: 4 - Beta
Classifier: Intended Audience :: Developers
Classifier: Topic :: Software Development :: Libraries :: Python Modules
Requires-Python: >=3.6
Provides-Extra: yaml
Requires-Dist: pyyaml; extra == "yaml"
Dynamic: author
Dynamic: home-page
Dynamic: requires-python
